pyv.py
pyv_file_running-1.0.2.dist-info/METADATA
pyv_file_running-1.0.2.dist-info/WHEEL
pyv_file_running-1.0.2.dist-info/entry_points.txt
pyv_file_running-1.0.2.dist-info/RECORD
