Metadata-Version: 2.4
Name: pyv_file_running
Version: 1.0.2
Summary: A module for '.pyv' file
Project-URL: homepage, https://github.com/Locked-chess-official/pyv
Author-email: Locked-chess-official <13140752715@163.com>
License: MIT
Requires-Python: >=3.7
